Metadata-Version: 1.1
Name: mathsplus
Version: 0.0.3
Summary: Extra maths functions.
Home-page: UNKNOWN
Author: Connor McHarg, Thomas Copland
Author-email: UNKNOWN
License: MIT
Keywords: maths
Platform: UNKNOWN
Classifier: License :: OSI Approved :: MIT License
Classifier: Operating System :: Microsoft :: Windows :: Windows 10
Classifier: Development Status :: 5 - Production/Stable
Classifier: Intended Audience :: Education
Classifier: Programming Language :: Python :: 3
